pyqa/__init__.py
pyqa/__main__.py
pyqa/cli.py
pyqa/constants.py
pyqa/erros.py
pyqa/pyqa.py
pyqa/utils.py
pyqa_y8l-0.3.8.dist-info/AUTHORS.rst
pyqa_y8l-0.3.8.dist-info/LICENSE
pyqa_y8l-0.3.8.dist-info/METADATA
pyqa_y8l-0.3.8.dist-info/WHEEL
pyqa_y8l-0.3.8.dist-info/entry_points.txt
pyqa_y8l-0.3.8.dist-info/top_level.txt
pyqa_y8l-0.3.8.dist-info/RECORD
