Metadata-Version: 2.1
Name: pyqa-y8l
Version: 0.3.8
Summary: Python console appliction that searches the internet for asnwers to coding problems
Home-page: https://github.com/yusufadell/pyqa
Author: Yusuf Adel
Author-email: yusufadell.dev@gmail.com
License: Apache Software License 2.0
Keywords: pyqa
Classifier: Development Status :: 2 - Pre-Alpha
Classifier: Intended Audience :: Developers
Classifier: License :: OSI Approved :: Apache Software License
Classifier: Natural Language :: English
Classifier: Programming Language :: Python :: 3
Classifier: Programming Language :: Python :: 3.6
Classifier: Programming Language :: Python :: 3.7
Classifier: Programming Language :: Python :: 3.8
Requires-Python: >=3.6
License-File: LICENSE
License-File: AUTHORS.rst
Requires-Dist: Click (>=7.0)
Requires-Dist: rich (>=12.6.0)
Requires-Dist: textual (>=0.4.0)
Requires-Dist: pyfiglet (>=0.8.post1)
